MANIFEST.in
Products.FCKeditor-configure.zcml
README.txt
setup.py
Products/__init__.py
Products.FCKeditor.egg-info/PKG-INFO
Products.FCKeditor.egg-info/SOURCES.txt
Products.FCKeditor.egg-info/dependency_links.txt
Products.FCKeditor.egg-info/entry_points.txt
Products.FCKeditor.egg-info/namespace_packages.txt
Products.FCKeditor.egg-info/not-zip-safe
Products.FCKeditor.egg-info/requires.txt
Products.FCKeditor.egg-info/top_level.txt
Products/FCKeditor/FckWidget.py
Products/FCKeditor/RichContentDemo.py
Products/FCKeditor/__init__.py
Products/FCKeditor/config.py
Products/FCKeditor/configure.zcml
Products/FCKeditor/kss_plugin.js
Products/FCKeditor/license.txt
Products/FCKeditor/utils.py
Products/FCKeditor/version.txt
Products/FCKeditor/Extensions/Install.py
Products/FCKeditor/Extensions/__init__.py
Products/FCKeditor/Extensions/updateFckUsers.py
Products/FCKeditor/_addons/plugins/FileIcon/fckplugin.js
Products/FCKeditor/_addons/plugins/FileIcon/fileicon.gif
Products/FCKeditor/_addons/plugins/FileIcon/fileicon.html
Products/FCKeditor/_addons/plugins/FileIcon/icons/ai.gif
Products/FCKeditor/_addons/plugins/FileIcon/icons/avi.gif
Products/FCKeditor/_addons/plugins/FileIcon/icons/bmp.gif
Products/FCKeditor/_addons/plugins/FileIcon/icons/cs.gif
Products/FCKeditor/_addons/plugins/FileIcon/icons/dll.gif
Products/FCKeditor/_addons/plugins/FileIcon/icons/doc.gif
Products/FCKeditor/_addons/plugins/FileIcon/icons/exe.gif
Products/FCKeditor/_addons/plugins/FileIcon/icons/fla.gif
Products/FCKeditor/_addons/plugins/FileIcon/icons/gif.gif
Products/FCKeditor/_addons/plugins/FileIcon/icons/html.gif
Products/FCKeditor/_addons/plugins/FileIcon/icons/ico.gif
Products/FCKeditor/_addons/plugins/FileIcon/icons/jpg.gif
Products/FCKeditor/_addons/plugins/FileIcon/icons/js.gif
Products/FCKeditor/_addons/plugins/FileIcon/icons/mdb.gif
Products/FCKeditor/_addons/plugins/FileIcon/icons/mp3.gif
Products/FCKeditor/_addons/plugins/FileIcon/icons/pdf.gif
Products/FCKeditor/_addons/plugins/FileIcon/icons/png.gif
Products/FCKeditor/_addons/plugins/FileIcon/icons/ppt.gif
Products/FCKeditor/_addons/plugins/FileIcon/icons/rdp.gif
Products/FCKeditor/_addons/plugins/FileIcon/icons/swf.gif
Products/FCKeditor/_addons/plugins/FileIcon/icons/txt.gif
Products/FCKeditor/_addons/plugins/FileIcon/icons/vsd.gif
