Metadata-Version: 1.0
Name: Products.FCKeditor
Version: 2.6.6.3
Summary: FCKeditor.Plone
Home-page: http://plone.org/products/fckeditor
Author: Ingeniweb
Author-email: support@ingeniweb.com
License: GPL
Keywords: web zope plone wysiwyg editor
Platform: UNKNOWN
Classifier: Framework :: Plone
Classifier: Programming Language :: Python
Classifier: Topic :: Software Development :: Libraries :: Python Modules
